firelet
