Metadata-Version: 1.1
Name: firelet
Version: 0.5.0a3
Summary: Distributed firewall management
Home-page: http://www.firelet.net/
Author: Federico Ceratto
Author-email: federico.ceratto@gmail.com
License: GPLv3+
Platform: Linux
Classifier: Environment :: Console
Classifier: Environment :: Web Environment
Classifier: License :: OSI Approved :: GNU General Public License v3 (GPLv3)
Classifier: Operating System :: POSIX :: Linux
Classifier: Programming Language :: Python
Classifier: Topic :: Security
